soilpy/__init__.py
soilpy-0.0.1.dist-info/METADATA
soilpy-0.0.1.dist-info/WHEEL
soilpy-0.0.1.dist-info/top_level.txt
soilpy-0.0.1.dist-info/RECORD
