Metadata-Version: 2.1
Name: soilpy
Version: 0.0.1
Summary: General Purpose Soil Mechanics Python Library
Home-page: https://github.com/groundworkai/soilpy
Author: Nick Machairas
Author-email: nick@groundwork.ai
License: UNKNOWN
Platform: UNKNOWN
Classifier: Programming Language :: Python :: 3
Classifier: License :: OSI Approved :: MIT License
Classifier: Operating System :: OS Independent
Requires-Python: >=3.7
